[
  {
    "type": "keyboard",
    "event": "d",
    "event_type": "down",
    "time": 0,
    "pressed_keys": [
      "d"
    ],
    "position": {
      "x": 98.0,
      "y": 36.0
    }
  },
  {
    "type": "keyboard",
    "event": "d",
    "event_type": "up",
    "time": 0.099,
    "pressed_keys": [],
    "position": {
      "x": 98.0,
      "y": 36.0
    }
  },
  {
    "type": "keyboard",
    "event": "4",
    "event_type": "down",
    "time": 0.443,
    "pressed_keys": [
      "4",
      "left"
    ],
    "position": {
      "x": 98.0,
      "y": 36.0
    }
  },
  {
    "type": "keyboard",
    "event": "left",
    "event_type": "down",
    "time": 0.443,
    "pressed_keys": [
      "4",
      "left"
    ],
    "position": {
      "x": 98.0,
      "y": 36.0
    }
  },
  {
    "type": "keyboard",
    "event": "space",
    "event_type": "down",
    "time": 1.698,
    "pressed_keys": [
      "4",
      "left",
      "space"
    ],
    "position": {
      "x": 90.0,
      "y": 35.0
    }
  },
  {
    "type": "keyboard",
    "event": "space",
    "event_type": "up",
    "time": 1.821,
    "pressed_keys": [
      "4",
      "left"
    ],
    "position": {
      "x": 84.0,
      "y": 33.0
    }
  },
  {
    "type": "keyboard",
    "event": "d",
    "event_type": "down",
    "time": 2.133,
    "pressed_keys": [
      "4",
      "d",
      "left"
    ],
    "position": {
      "x": 79.0,
      "y": 33.0
    }
  },
  {
    "type": "keyboard",
    "event": "d",
    "event_type": "up",
    "time": 2.229,
    "pressed_keys": [
      "4",
      "left"
    ],
    "position": {
      "x": 79.0,
      "y": 33.0
    }
  },
  {
    "type": "keyboard",
    "event": "space",
    "event_type": "down",
    "time": 3.37,
    "pressed_keys": [
      "4",
      "left",
      "space"
    ],
    "position": {
      "x": 64.0,
      "y": 38.0
    }
  },
  {
    "type": "keyboard",
    "event": "space",
    "event_type": "up",
    "time": 3.511,
    "pressed_keys": [
      "4",
      "left"
    ],
    "position": {
      "x": 57.0,
      "y": 36.0
    }
  },
  {
    "type": "keyboard",
    "event": "d",
    "event_type": "down",
    "time": 3.669,
    "pressed_keys": [
      "4",
      "d",
      "left"
    ],
    "position": {
      "x": 51.0,
      "y": 37.0
    }
  },
  {
    "type": "keyboard",
    "event": "d",
    "event_type": "up",
    "time": 3.837,
    "pressed_keys": [
      "4",
      "left"
    ],
    "position": {
      "x": 46.0,
      "y": 39.0
    }
  },
  {
    "type": "keyboard",
    "event": "space",
    "event_type": "down",
    "time": 4.899,
    "pressed_keys": [
      "4",
      "left",
      "space"
    ],
    "position": {
      "x": 40.0,
      "y": 39.0
    }
  },
  {
    "type": "keyboard",
    "event": "space",
    "event_type": "up",
    "time": 5.003,
    "pressed_keys": [
      "4",
      "left"
    ],
    "position": {
      "x": 37.0,
      "y": 38.0
    }
  },
  {
    "type": "keyboard",
    "event": "d",
    "event_type": "down",
    "time": 5.232,
    "pressed_keys": [
      "4",
      "d",
      "left"
    ],
    "position": {
      "x": 26.0,
      "y": 37.0
    }
  },
  {
    "type": "keyboard",
    "event": "d",
    "event_type": "up",
    "time": 5.357,
    "pressed_keys": [
      "4",
      "left"
    ],
    "position": {
      "x": 20.0,
      "y": 39.0
    }
  },
  {
    "type": "keyboard",
    "event": "shift",
    "event_type": "down",
    "time": 6.713,
    "pressed_keys": [
      "4",
      "left",
      "shift"
    ],
    "position": {
      "x": 11.0,
      "y": 39.0
    }
  },
  {
    "type": "keyboard",
    "event": "shift",
    "event_type": "up",
    "time": 6.848,
    "pressed_keys": [
      "4",
      "left"
    ],
    "position": {
      "x": 10.0,
      "y": 37.0
    }
  },
  {
    "type": "keyboard",
    "event": "4",
    "event_type": "up",
    "time": 7.004,
    "pressed_keys": [],
    "position": {
      "x": 10.0,
      "y": 37.0
    }
  },
  {
    "type": "keyboard",
    "event": "left",
    "event_type": "up",
    "time": 7.004,
    "pressed_keys": [],
    "position": {
      "x": 10.0,
      "y": 37.0
    }
  },
  {
    "type": "keyboard",
    "event": "4",
    "event_type": "down",
    "time": 7.245,
    "pressed_keys": [
      "4",
      "left",
      "shift"
    ],
    "position": {
      "x": 8.0,
      "y": 17.0
    }
  },
  {
    "type": "keyboard",
    "event": "left",
    "event_type": "down",
    "time": 7.245,
    "pressed_keys": [
      "4",
      "left",
      "shift"
    ],
    "position": {
      "x": 8.0,
      "y": 17.0
    }
  },
  {
    "type": "keyboard",
    "event": "shift",
    "event_type": "down",
    "time": 7.245,
    "pressed_keys": [
      "4",
      "left",
      "shift"
    ],
    "position": {
      "x": 8.0,
      "y": 17.0
    }
  },
  {
    "type": "keyboard",
    "event": "shift",
    "event_type": "up",
    "time": 7.404,
    "pressed_keys": [
      "4",
      "left"
    ],
    "position": {
      "x": 8.0,
      "y": 9.0
    }
  },
  {
    "type": "keyboard",
    "event": "d",
    "event_type": "down",
    "time": 7.572,
    "pressed_keys": [
      "d"
    ],
    "position": {
      "x": 8.0,
      "y": 9.0
    }
  },
  {
    "type": "keyboard",
    "event": "4",
    "event_type": "up",
    "time": 7.572,
    "pressed_keys": [
      "d"
    ],
    "position": {
      "x": 8.0,
      "y": 9.0
    }
  },
  {
    "type": "keyboard",
    "event": "left",
    "event_type": "up",
    "time": 7.572,
    "pressed_keys": [
      "d"
    ],
    "position": {
      "x": 8.0,
      "y": 9.0
    }
  },
  {
    "type": "keyboard",
    "event": "d",
    "event_type": "up",
    "time": 7.738,
    "pressed_keys": [],
    "position": null
  },
  {
    "type": "keyboard",
    "event": "right",
    "event_type": "down",
    "time": 8.072,
    "pressed_keys": [
      "right",
      "6"
    ],
    "position": {
      "x": 6.0,
      "y": 0.0
    }
  },
  {
    "type": "keyboard",
    "event": "6",
    "event_type": "down",
    "time": 8.072,
    "pressed_keys": [
      "right",
      "6"
    ],
    "position": {
      "x": 6.0,
      "y": 0.0
    }
  },
  {
    "type": "keyboard",
    "event": "d",
    "event_type": "down",
    "time": 10.408,
    "pressed_keys": [
      "d",
      "right",
      "6"
    ],
    "position": {
      "x": 24.0,
      "y": 17.0
    }
  },
  {
    "type": "keyboard",
    "event": "d",
    "event_type": "up",
    "time": 10.574,
    "pressed_keys": [
      "right",
      "6"
    ],
    "position": {
      "x": 26.0,
      "y": 17.0
    }
  },
  {
    "type": "keyboard",
    "event": "space",
    "event_type": "down",
    "time": 11.44,
    "pressed_keys": [
      "6",
      "right",
      "space"
    ],
    "position": {
      "x": 26.0,
      "y": 17.0
    }
  },
  {
    "type": "keyboard",
    "event": "space",
    "event_type": "up",
    "time": 11.576,
    "pressed_keys": [
      "right",
      "6"
    ],
    "position": {
      "x": 32.0,
      "y": 14.0
    }
  },
  {
    "type": "keyboard",
    "event": "d",
    "event_type": "down",
    "time": 11.919,
    "pressed_keys": [
      "d",
      "right",
      "6"
    ],
    "position": {
      "x": 48.0,
      "y": 17.0
    }
  },
  {
    "type": "keyboard",
    "event": "d",
    "event_type": "up",
    "time": 12.075,
    "pressed_keys": [
      "right",
      "6"
    ],
    "position": {
      "x": 50.0,
      "y": 17.0
    }
  },
  {
    "type": "keyboard",
    "event": "space",
    "event_type": "down",
    "time": 13.076,
    "pressed_keys": [
      "6",
      "right",
      "space"
    ],
    "position": {
      "x": 52.0,
      "y": 17.0
    }
  },
  {
    "type": "keyboard",
    "event": "space",
    "event_type": "up",
    "time": 13.13,
    "pressed_keys": [
      "right",
      "6"
    ],
    "position": {
      "x": 57.0,
      "y": 15.0
    }
  },
  {
    "type": "keyboard",
    "event": "d",
    "event_type": "down",
    "time": 13.459,
    "pressed_keys": [
      "d",
      "right",
      "6"
    ],
    "position": {
      "x": 73.0,
      "y": 17.0
    }
  },
  {
    "type": "keyboard",
    "event": "d",
    "event_type": "up",
    "time": 13.604,
    "pressed_keys": [
      "right",
      "6"
    ],
    "position": {
      "x": 78.0,
      "y": 21.0
    }
  },
  {
    "type": "keyboard",
    "event": "space",
    "event_type": "down",
    "time": 14.529,
    "pressed_keys": [
      "6",
      "right",
      "space"
    ],
    "position": {
      "x": 82.0,
      "y": 21.0
    }
  },
  {
    "type": "keyboard",
    "event": "space",
    "event_type": "up",
    "time": 14.641,
    "pressed_keys": [
      "right",
      "6"
    ],
    "position": {
      "x": 84.0,
      "y": 20.0
    }
  },
  {
    "type": "keyboard",
    "event": "right",
    "event_type": "up",
    "time": 15.025,
    "pressed_keys": [],
    "position": {
      "x": 101.0,
      "y": 19.0
    }
  },
  {
    "type": "keyboard",
    "event": "6",
    "event_type": "up",
    "time": 15.025,
    "pressed_keys": [],
    "position": {
      "x": 101.0,
      "y": 19.0
    }
  },
  {
    "type": "keyboard",
    "event": "4",
    "event_type": "down",
    "time": 15.161,
    "pressed_keys": [
      "4",
      "left"
    ],
    "position": {
      "x": 101.0,
      "y": 19.0
    }
  },
  {
    "type": "keyboard",
    "event": "left",
    "event_type": "down",
    "time": 15.161,
    "pressed_keys": [
      "4",
      "left"
    ],
    "position": {
      "x": 101.0,
      "y": 19.0
    }
  },
  {
    "type": "keyboard",
    "event": "4",
    "event_type": "up",
    "time": 15.662,
    "pressed_keys": [],
    "position": {
      "x": 103.0,
      "y": 36.0
    }
  },
  {
    "type": "keyboard",
    "event": "left",
    "event_type": "up",
    "time": 15.662,
    "pressed_keys": [],
    "position": {
      "x": 103.0,
      "y": 36.0
    }
  },
  {
    "type": "keyboard",
    "event": "d",
    "event_type": "down",
    "time": 15.872,
    "pressed_keys": [
      "d"
    ],
    "position": {
      "x": 102.0,
      "y": 36.0
    }
  },
  {
    "type": "keyboard",
    "event": "d",
    "event_type": "up",
    "time": 15.997,
    "pressed_keys": [],
    "position": {
      "x": 102.0,
      "y": 36.0
    }
  }
]